PREN_flawas/ColorRecognition.py
PREN_flawas/DataPreparation.py
PREN_flawas/DataSend.py
PREN_flawas/DataVerify.py
PREN_flawas/Display.py
PREN_flawas/Energy.py
PREN_flawas/Engine.py
PREN_flawas/__init__.py
PREN_flawas/logger.conf
PREN_flawas/pic/Font.ttc
PREN_flawas/pic/background.bmp
PREN_flawas/pic/qrcode.bmp
PREN_flawas/waveshare_epd/epd1in54_V2.py
PREN_flawas/waveshare_epd/epdconfig.py
pren_flawas-0.0.71.dist-info/METADATA
pren_flawas-0.0.71.dist-info/WHEEL
pren_flawas-0.0.71.dist-info/licenses/LICENSE
pren_flawas-0.0.71.dist-info/RECORD
