Metadata-Version: 2.3
Name: PREN_flawas
Version: 0.0.71
Summary: A small package used for a project at HSLU Luzern.
Project-URL: Homepage, https://github.com/flawas/PREN_Module
Project-URL: Issues, https://github.com/flawas/PREN_Module/issues
Author-email: Flavio Waser <waserflavio@gmail.com>
License-File: LICENSE
Classifier: License :: OSI Approved :: MIT License
Classifier: Operating System :: OS Independent
Classifier: Programming Language :: Python :: 3
Requires-Python: >=3.8
